{
	"datelist": [{
		"month": "2018-10",
		"date": [{
			"day": "2018-10-10",
			"statusPhone": "true",
			"statusVisit": "false",
			"statusVisited": "true",
			"statusCooperation": "false",
			"statusformal": "true"
		}, {
			"day": "2018-10-11",
			"statusPhone": "false",
			"statusVisit": "false",
			"statusVisited": "true",
			"statusCooperation": "true",
			"statusformal": "true"
		}, {
			"day": "2018-10-12",
			"statusPhone": "false",
			"statusVisit": "false",
			"statusVisited": "true",
			"statusCooperation": "true",
			"statusformal": "false"
		}, {
			"day": "2018-10-1",
			"statusPhone": "false",
			"statusVisit": "false",
			"statusVisited": "true",
			"statusCooperation": "true",
			"statusformal": "true"
		}, {
			"day": "2018-10-16",
			"statusPhone": "false",
			"statusVisit": "false",
			"statusVisited": "false",
			"statusCooperation": "true",
			"statusformal": "true"
		}, {
			"day": "2018-10-29",
			"statusPhone": "false",
			"statusVisit": "false",
			"statusVisited": "true",
			"statusCooperation": "true",
			"statusformal": "true"
		}]
	}, {
		"month": "2018-11",
		"date": [{
			"day": "2018-11-1",
			"statusPhone": "false",
			"statusVisit": "true",
			"statusVisited": "true",
			"statusCooperation": "true",
			"statusformal": "false"
		}, {
			"day": "2018-11-11",
			"statusPhone": "false",
			"statusVisit": "true",
			"statusVisited": "true",
			"statusCooperation": "false",
			"statusformal": "false"
		}, {
			"day": "2018-11-14",
			"statusPhone": "true",
			"statusVisit": "true",
			"statusVisited": "true",
			"statusCooperation": "false",
			"statusformal": "false"
		}, {
			"day": "2018-11-19",
			"statusPhone": "true",
			"statusVisit": "true",
			"statusVisited": "false",
			"statusCooperation": "false",
			"statusformal": "false"
		}, {
			"day": "2018-11-2",
			"statusPhone": "true",
			"statusVisit": "false",
			"statusVisited": "true",
			"statusCooperation": "false",
			"statusformal": "false"
		}]
	}, {
		"month": "2018-12",
		"date": [{
			"day": "2018-12-5",
			"statusPhone": "false",
			"statusVisit": "false",
			"statusVisited": "true",
			"statusCooperation": "true",
			"statusformal": "false"
		}, {
			"day": "2018-12-20",
			"statusPhone": "true",
			"statusVisit": "false",
			"statusVisited": "false",
			"statusCooperation": "true",
			"statusformal": "true"
		}, {
			"day": "2018-12-3",
			"statusPhone": "false",
			"statusVisit": "false",
			"statusVisited": "false",
			"statusCooperation": "true",
			"statusformal": "true"
		}
		, {
				"day": "2018-12-1",
				"statusPhone": "true",
				"statusVisit": "false",
				"statusVisited": "false",
				"statusCooperation": "true",
				"statusformal": "true"
			}, {
				"day": "2018-12-24",
				"statusPhone": "false",
				"statusVisit": "false",
				"statusVisited": "false",
				"statusCooperation": "true",
				"statusformal": "false"
			}]
	}]
}